gencc/__init__.py
gencc/gencc.py
gencc-1.0.1.dist-info/LICENSE
gencc-1.0.1.dist-info/METADATA
gencc-1.0.1.dist-info/WHEEL
gencc-1.0.1.dist-info/entry_points.txt
gencc-1.0.1.dist-info/top_level.txt
gencc-1.0.1.dist-info/RECORD
