Metadata-Version: 2.1
Name: gencc
Version: 1.0.1
Summary: CC GENERATOR FOR BIN
Home-page: https://github.com/AKXVAU
Author: AKXVAU
Author-email: admin@itzakx.ml
License: MIT
Keywords: GENCC,BIN,CC GENERATOR,CRADIT CARD NUMBER,AKXVAU,DCBD04,DEVS COMMUNITY,DEV COMMUNITY,MOHAMMAD ALAMIN
Classifier: Development Status :: 4 - Beta
Classifier: Intended Audience :: Developers
Classifier: Topic :: Software Development :: Libraries :: Python Modules
Classifier: License :: OSI Approved :: MIT License
Classifier: Programming Language :: Python :: 3
Classifier: Operating System :: OS Independent
Classifier: Environment :: Console
Requires-Python: >=3.9
License-File: LICENSE
Requires-Dist: lolcat
